[{"judul":"modele cv 2018","link":"http:\/\/www.serrurier13015.fr\/wp-content\/uploads\/2017\/11\/Modele_CV_etudiant_gris_souris.png","thumb":"https:\/\/tse4.mm.bing.net\/th?id=OIP.inEH1D2sHXDc3AIySb2fWQHaKg&pid=Api&P=0&w=300&h=300"},{"judul":"l u0026 39  u0152il du recruteur","link":"https:\/\/oeildurecruteur.ca\/wp-content\/uploads\/2016\/01\/Cadlallure.png","thumb":"https:\/\/tse1.mm.bing.net\/th?id=OIP.EmJvOpZKoCzWDAlThsDC6AHaEq&pid=Api&P=0&w=300&h=300"},{"judul":"mod u00e8les de cv originaux gratuits  new","link":"https:\/\/www.qapa.fr\/news\/wp-content\/uploads\/Mod%C3%A8le-CV-original-Bleu--e1435076418128.png","thumb":"https:\/\/tse4.mm.bing.net\/th?id=OIP.y32O1IS7Bnfi_1jFfYCAtgHaKW&pid=Api&P=0&w=300&h=300"},{"judul":"cv gratuit rouge","link":"http:\/\/www.modele-curriculum-vitae.com\/images\/cv-gratuit-rouge_3.jpg","thumb":"https:\/\/tse2.mm.bing.net\/th?id=OIP.TxkgtBphAnYKCpgKTecdOgHaKa&pid=Api&P=0&w=300&h=300"},{"judul":"cv etudiant belgique","link":"http:\/\/www.modele-curriculum-vitae.com\/images\/cv-etudiant-belgique_4.jpg","thumb":"https:\/\/tse1.mm.bing.net\/th?id=OIP.MUjpoNiHxWmtj4UV5F2z5wHaJY&pid=Api&P=0&w=300&h=300"},{"judul":"garage de poche jip u00e9  4 cv brissonneau  u0026 lotz roadster 1957","link":"https:\/\/2.bp.blogspot.com\/_J43t48V_cGE\/S_1SGjMU60I\/AAAAAAAARjc\/dOczHBjvs9U\/s1600\/6.jpg","thumb":"https:\/\/tse2.mm.bing.net\/th?id=OIP.2wUBgr-40jLnhP0G-hdnKAHaE1&pid=Api&P=0&w=300&h=300"},{"judul":"cv en ligne gratuit belgique","link":"http:\/\/www.modele-curriculum-vitae.com\/images\/cv-en-ligne-gratuit-belgique_2.jpg","thumb":"https:\/\/tse2.mm.bing.net\/th?id=OIP.rC_wojdcfK2rMFrLx_icmgHaKe&pid=Api&P=0&w=300&h=300"},{"judul":"raids automobiles sahariens  africains et autres","link":"http:\/\/images.forum-auto.com\/mesimages\/1018677\/CCI1006201100014.jpg","thumb":"https:\/\/tse4.mm.bing.net\/th?id=OIP.YUlVgW8MuWTp7oGN466BNwHaEJ&pid=Api&P=0&w=300&h=300"},{"judul":"garage de poche jip u00e9  panhard  u0026 levassor 1902","link":"http:\/\/4.bp.blogspot.com\/-tQBB_C8dO34\/U_4jRQ2r3II\/AAAAAAAAq6o\/Dj3sOoj08S8\/s1600\/82_.jpg","thumb":"https:\/\/tse4.mm.bing.net\/th?id=OIP.8K-1eLdAfbqdUsMyt7iqFgHaF6&pid=Api&P=0&w=300&h=300"},{"judul":"en mod u00e8le r u00e9duit  morgan 4  4 tamiya ech 1  24","link":"http:\/\/1.bp.blogspot.com\/-XeRgP46Sv38\/VGjdcaz_3OI\/AAAAAAAAEWQ\/ZRzk-RfRbn4\/s1600\/Composition15.jpg","thumb":"https:\/\/tse1.mm.bing.net\/th?id=OIP.00OOZvSsxc0rpRQYzlvbigHaFH&pid=Api&P=0&w=300&h=300"},{"judul":"en mod u00e8le r u00e9duit  la cagole blanche","link":"http:\/\/1.bp.blogspot.com\/-n6VtmPXItVs\/U0QVfPnw-9I\/AAAAAAAADF4\/RhEp3bGJbag\/s1600\/IMG_4657.JPG","thumb":"https:\/\/tse2.mm.bing.net\/th?id=OIP.1QvdXOaj49fLZ9OKpGxo0wHaD7&pid=Api&P=0&w=300&h=300"},{"judul":"demande d u0026 39 homologation d u0026 39 un circuit","link":"http:\/\/static.documentissime.fr\/images\/apercus-cerfas\/demande-d-homologation-d-un-circuit-524.png","thumb":"https:\/\/tse2.mm.bing.net\/th?id=OIP.0Md1ZKSz4Jd7we1GJ4UxpgHaKf&pid=Api&P=0&w=300&h=300"},{"judul":"en mod u00e8le r u00e9duit  camion  u0026quot huile d u0026 39 olive dorado u0026quot","link":"http:\/\/2.bp.blogspot.com\/-kn25K-wK2AI\/U0QYAKkkHwI\/AAAAAAAADGk\/6Cb9QVZ8PIc\/s1600\/camion+DODO+022.jpg","thumb":"https:\/\/tse1.mm.bing.net\/th?id=OIP.tMUqcZbzDohA4Y-c6T-pFQHaE_&pid=Api&P=0&w=300&h=300"},{"judul":"suez environnement","link":"http:\/\/www.journaldunet.com\/management\/communication\/cartes-de-voeux-2010-des-entreprises\/image\/suez-environnement-538403.jpg","thumb":"https:\/\/tse1.mm.bing.net\/th?id=OIP.LXOjlwEQwm3OBka35Dz_xQHaE8&pid=Api&P=0&w=300&h=300"}]