[{"judul":"41 inspirant image de comp u00e9tence esth u00e9ticienne cv","link":"https:\/\/unitehereforchange.org\/wp-content\/uploads\/2018\/12\/competence-estheticienne-cv-frais-image-des-livres-of-competence-estheticienne-cv.jpg","thumb":"https:\/\/tse2.mm.bing.net\/th?id=OIP.DndVeXj3ZH8xzKCtqvysCgAAAA&pid=Api&P=0&w=300&h=300"},{"judul":"13  cv esth u00e9ticienne gratuit","link":"https:\/\/redditrpics.com\/wp-content\/uploads\/Telechargement-Gratuit-Cv-Original-A-Modele-Cv-Gratuit-Word-Pdf-1.jpg","thumb":"https:\/\/tse4.mm.bing.net\/th?id=OIP.n8OspxLOkwYj6Q2rNsM3AgHaKc&pid=Api&P=0&w=300&h=300"}]