[{"judul":"free printable cvs job application form","link":"http:\/\/www.application.careers\/jobimg\/cvs-application-form-l1.png","thumb":"https:\/\/tse1.mm.bing.net\/th?id=OIP.ZpPQiMOto_0cuTXsn878hAHaJl&pid=Api&P=0&w=300&h=300"},{"judul":"the top architecture r u00e9sum u00e9  cv designs","link":"https:\/\/images.adsttc.com\/media\/images\/57b3\/7970\/e58e\/ce7d\/c100\/002f\/newsletter\/2016-08-16.jpg?1471379820","thumb":"https:\/\/tse4.mm.bing.net\/th?id=OIP.hwMfRiJGmv1AsgUqoPJbIAHaEU&pid=Api&P=0&w=300&h=300"},{"judul":"10  cv format sinhala","link":"http:\/\/lettersetup.com\/wp-content\/uploads\/2018\/09\/Sinhala-Job-Application-3.jpg","thumb":"https:\/\/tse2.mm.bing.net\/th?id=OIP.qmF-vtD1skTaSl6pEtkjBAHaKB&pid=Api&P=0&w=300&h=300"},{"judul":"how to write a winning curriculum vitae","link":"http:\/\/ecological.blogs.panda.org\/wp-content\/uploads\/sites\/6\/2014\/05\/CV.jpg","thumb":"https:\/\/tse3.mm.bing.net\/th?id=OIP.uU7Vu0kAfk4HF9MMcSpD8gHaE7&pid=Api&P=0&w=300&h=300"},{"judul":"meteorologist cover letter sample","link":"https:\/\/www.livecareer.co.uk\/wp-content\/uploads\/2016\/09\/meteorologist.png","thumb":"https:\/\/tse1.mm.bing.net\/th?id=OIP.ppObSyCwm4sGeHpglw4wLAHaG1&pid=Api&P=0&w=300&h=300"},{"judul":"6  formats and cv examples for human resource jobs","link":"https:\/\/www.doctemplates.net\/wp-content\/uploads\/2017\/03\/Human-Resources-Officer-CV.png","thumb":"https:\/\/tse1.mm.bing.net\/th?id=OIP.irU39UMrKLMBDEc1x8fQagHaKT&pid=Api&P=0&w=300&h=300"},{"judul":"a retail fashion company requires managers  merchandisers","link":"http:\/\/www.pakistanjobsbank.com\/Pakistan\/Jobs\/Jang\/Ad_Jang_Job_20130203_029.gif","thumb":"https:\/\/tse1.mm.bing.net\/th?id=OIP.enSA9M8Vt0j8OoHRDXb96QHaGC&pid=Api&P=0&w=300&h=300"},{"judul":"free printable bed bath and beyond job application form","link":"https:\/\/www.application.careers\/jobimg\/bed-bath-and-beyond-application-form-l1.png","thumb":"https:\/\/tse3.mm.bing.net\/th?id=OIP.z_G84OM8Z4yMW1a38xnqWwHaJl&pid=Api&P=0&w=300&h=300"},{"judul":"detention officer cover letter sample","link":"https:\/\/www.livecareer.co.uk\/wp-content\/uploads\/2016\/09\/detention-officer.png","thumb":"https:\/\/tse1.mm.bing.net\/th?id=OIP.wDuI49f7kLCeniKMrbZZ-gHaHP&pid=Api&P=0&w=300&h=300"},{"judul":"administration resume template    administrative assistant","link":"https:\/\/i.pinimg.com\/originals\/5e\/09\/68\/5e0968eb9a3b5e27f4e2c15bc6c4b0b5.png","thumb":"https:\/\/tse4.mm.bing.net\/th?id=OIP.4fpi9yUKaKbdZpEWkpOq2wHaLG&pid=Api&P=0&w=300&h=300"},{"judul":"vacancies","link":"https:\/\/www.bowerpark.co.uk\/wp-content\/uploads\/2017\/06\/New-uniform-photographs-12.jpg","thumb":"https:\/\/tse1.mm.bing.net\/th?id=OIP.nB9HiFYY7XdpFleuZwo4sAHaFj&pid=Api&P=0&w=300&h=300"},{"judul":"immigration","link":"https:\/\/www.cvplaza.com\/wp-content\/uploads\/2016\/12\/immigration-advisor-cv-template-2.png","thumb":"https:\/\/tse2.mm.bing.net\/th?id=OIP.zT1poBXXpApbvGEa-TwCtgHaLr&pid=Api&P=0&w=300&h=300"},{"judul":"how to become an ordained minister in washington state","link":"http:\/\/photos.demandstudios.com\/getty\/article\/251\/107\/56964615.jpg","thumb":"https:\/\/tse3.mm.bing.net\/th?id=OIP._N5Zilm7wHoOmWohgVrojQHaJ3&pid=Api&P=0&w=300&h=300"},{"judul":"request letter","link":"https:\/\/www.livecareer.co.uk\/wp-content\/uploads\/2016\/09\/request-letter.png","thumb":"https:\/\/tse3.mm.bing.net\/th?id=OIP.f2el2I5SJBSqjRS5K2NNYgHaG1&pid=Api&P=0&w=300&h=300"}]