[{"judul":"5 outils gratuits pour cr u00e9er un cv en ligne","link":"http:\/\/allweb2.com\/wp-content\/uploads\/2013\/11\/Votre-profil-LinkedIn-2013-11-20-07-45-54.jpg","thumb":"https:\/\/tse1.mm.bing.net\/th?id=OIP.DunyziJzXjaCX1OxoodHZQHaFu&pid=Api&P=0&w=300&h=300"},{"judul":"linkedin   10 outils m u00e9connus pour booster votre carri u00e8re","link":"https:\/\/img-0.journaldunet.com\/i2Cn26F8eDVUY5e11r4z0zvxRuo=\/600x\/smart\/34947dd936034a0fa8878182e696166e\/ccmcms-jdn\/1848851.jpg","thumb":"https:\/\/tse3.mm.bing.net\/th?id=OIP.yRbu6T8v9n8ThFHfqNtyjgHaHa&pid=Api&P=0&w=300&h=300"},{"judul":"screenshot de site sans desktop","link":"https:\/\/www.nicolasjean.fr\/wp-content\/uploads\/2013\/10\/Programmer-la-cr%C3%A9ation-de-site.htm_20131126092501-e1385454335420-640x298.png","thumb":"https:\/\/tse3.mm.bing.net\/th?id=OIP.zq3HRIkicT-UJMcHyay9oQHaDc&pid=Api&P=0&w=300&h=300"}]