[{"judul":"cv type femme de chambre","link":"http:\/\/www.modele-curriculum-vitae.com\/images\/cv-type-femme-de-chambre_3.jpg","thumb":"https:\/\/tse2.mm.bing.net\/th?id=OIP.lsNO-I9YyJI-4bJDcliUHgHaJa&pid=Api&P=0&w=300&h=300"},{"judul":"cv femme de chambre avec les meilleures collections d u0026 39 images","link":"http:\/\/www.journaldespalaces.com\/formulaires\/photos\/hotels\/55_Brochure_2017.PNG","thumb":"https:\/\/tse1.mm.bing.net\/th?id=OIP.rlmykDiFRKIw5a86WjcncgHaFh&pid=Api&P=0&w=300&h=300"},{"judul":"lettre de motivation femme de chambre","link":"http:\/\/southerngroupproperty.info\/wp-content\/uploads\/2018\/12\/lettre-de-motivation-femme-chambre-modele.jpg","thumb":"https:\/\/tse1.mm.bing.net\/th?id=OIP.1mR3CnSD6PY9XLq7rsookgHaJg&pid=Api&P=0&w=300&h=300"},{"judul":"modele cv cip","link":"http:\/\/www.modelede.fr\/wp-content\/uploads\/2015\/08\/modele-cv-master-2-4-723x1024.jpg","thumb":"https:\/\/tse3.mm.bing.net\/th?id=OIP.WhdZzAx-X22PTd5XwNRlFAHaKf&pid=Api&P=0&w=300&h=300"},{"judul":"les 25 meilleures id u00e9es de la cat u00e9gorie assistante","link":"https:\/\/i.pinimg.com\/736x\/55\/28\/56\/552856f9f9eb4444691bbf031f27ac15--erp-elixir.jpg","thumb":"https:\/\/tse3.mm.bing.net\/th?id=OIP.Nlb_aOGhl6jxjjD4zaidPQHaGM&pid=Api&P=0&w=300&h=300"},{"judul":"exemple cv administrateur systeme","link":"http:\/\/image.slidesharecdn.com\/cvrgis2013-directeur-130308165745-phpapp01\/95\/cv-dsi-nantes-1-638.jpg?cb=1362761899","thumb":"https:\/\/tse4.mm.bing.net\/th?id=OIP.xGqvpX-DjH6s_5SLm8Q7oAHaKe&pid=Api&P=0&w=300&h=300"},{"judul":"modele lettre de motivation nettoyage","link":"http:\/\/www.lettre-utile.fr\/wp-content\/uploads\/2016\/08\/candidature-agent-nettoyage-debutant.gif","thumb":"https:\/\/tse2.mm.bing.net\/th?id=OIP.Bf4HwqtmLnJ8yqpGSsD8UwHaKe&pid=Api&P=0&w=300&h=300"},{"judul":"lettre de motivation bio","link":"http:\/\/www.laboite-cv.fr\/wp-content\/uploads\/2018\/12\/lettre-motivation-bafa-gratuit-lettre-de-motivation-pour-bafa-exemple-lettre-de-motivation-pour-of-lettre-motivation-bafa.jpg","thumb":"https:\/\/tse2.mm.bing.net\/th?id=OIP.EyqSK182t20GLJWvDmnzEAHaJ1&pid=Api&P=0&w=300&h=300"},{"judul":"exemple dannonce de recrutement","link":"https:\/\/flexonics.org\/wp-content\/uploads\/2018\/10\/exemple-d-un-cv-exemple-annonce-de-recrutement-modc2a8le-materiel-de-coiffure-a-of-exemple-d-un-cv.jpg","thumb":"https:\/\/tse2.mm.bing.net\/th?id=OIP.W4idVWqIqagIsFCr-eEB6QHaE8&pid=Api&P=0&w=300&h=300"},{"judul":"exemple lettre de motivation nettoyage","link":"http:\/\/www.lettre-utile.fr\/wp-content\/uploads\/2016\/08\/candidature-agent-nettoyage-industriel.gif","thumb":"https:\/\/tse1.mm.bing.net\/th?id=OIP.iQUy-4iYehN_9YGFy4RNMwHaKe&pid=Api&P=0&w=300&h=300"}]