[{"judul":"speech language pathologist resume sample","link":"https:\/\/i.pinimg.com\/736x\/17\/88\/90\/17889088e2fccfa2e496cc71d7009f0b--perfect-resume-resume-examples.jpg","thumb":"https:\/\/tse1.mm.bing.net\/th?id=OIP.jho4l9pQX8rC2RY2khsJmQHaJl&pid=Api&P=0&w=300&h=300"},{"judul":"chronological cv  templates   resume templates","link":"https:\/\/resume.modelocurriculum.net\/wp-content\/uploads\/2010\/03\/chronologicaltemplate31.jpg","thumb":"https:\/\/tse1.mm.bing.net\/th?id=OIP.1NJ0dQBzdpDn-1pPdh8n0gHaKc&pid=Api&P=0&w=300&h=300"},{"judul":"import export coordinator cv sample","link":"https:\/\/www.myperfectcv.co.uk\/wp-content\/uploads\/2016\/09\/import-export-coordinator-cv-sample.jpg","thumb":"https:\/\/tse3.mm.bing.net\/th?id=OIP.Bs3cEid4Zl6wElI6U2K58AHaKV&pid=Api&P=0&w=300&h=300"},{"judul":"cv templates  chronological 3   resume templates","link":"https:\/\/resume.modelocurriculum.net\/wp-content\/uploads\/2010\/03\/chronologicalcv3maroon.jpg","thumb":"https:\/\/tse2.mm.bing.net\/th?id=OIP.9bpTqZdcHt0RLTPIhDgerAAAAA&pid=Api&P=0&w=300&h=300"},{"judul":"15 voorbeelden van creatieve cv u0026 39 s","link":"https:\/\/www.marketing-communicatie-vacatures.nl\/uploads\/afbeeldingen\/Carriere%20Blog\/15%20creatieve%20cvu0027s\/cv_Paolo_Zupin.jpg","thumb":"https:\/\/tse2.mm.bing.net\/th?id=OIP.DfN1VEnsbuPz-0w1DbiKlQHaKe&pid=Api&P=0&w=300&h=300"},{"judul":"sample flight attendant resume","link":"https:\/\/images.sampletemplates.com\/wp-content\/uploads\/2016\/12\/12172911\/Corporate-Flight-Attendant-Resume.jpg","thumb":"https:\/\/tse1.mm.bing.net\/th?id=OIP.CyDSEYUsLcFI8N3KqxeCKAHaJA&pid=Api&P=0&w=300&h=300"},{"judul":"administrative resume examples sample template example","link":"https:\/\/i.pinimg.com\/originals\/7f\/84\/ca\/7f84caf2fbf61344abb76621e114c230.jpg","thumb":"https:\/\/tse1.mm.bing.net\/th?id=OIP.7vvyMGQ3VTWnz78BteUXfwHaKi&pid=Api&P=0&w=300&h=300"},{"judul":"receptionist resume sample","link":"https:\/\/coda.newjobs.com\/api\/imagesproxy\/ms\/seo-media\/us\/resume-images\/receptionist.jpg","thumb":"https:\/\/tse4.mm.bing.net\/th?id=OIP.ei8i-HS3U5w60DcYOfjSTQHaJl&pid=Api&P=0&w=300&h=300"},{"judul":"net open source projects recommended  accord  aforge","link":"http:\/\/www.programering.com\/images\/remote\/ZnJvbT1jbmJsb2dzJnVybD13WnVCbkxsWnpZd0FqTXhZVFo1UVRZM0lHTmhGbVo0UVRPM1lqWndRV04ySVdNakJUTDJNRE94a1RNekV6TDVBek14QWpNdlV6TTJFek4wOHladnhtWXYwMmJqNXladnhtWTBsbWJqNXljbGRXWXRsMkx2b0RjMFJIYQ.jpg","thumb":"https:\/\/tse3.mm.bing.net\/th?id=OIP.-XTUDi5rxBtIWwLgQLknJgHaF4&pid=Api&P=0&w=300&h=300"},{"judul":"resume builder","link":"https:\/\/www.resumeviking.com\/wp-content\/uploads\/2018\/01\/HVAC-Technician-Experiences-Resume-Example.jpg","thumb":"https:\/\/tse1.mm.bing.net\/th?id=OIP.9fwXctXf9irdferZcBmswwHaKe&pid=Api&P=0&w=300&h=300"},{"judul":"cv templates  chronological 4   resume templates","link":"https:\/\/resume.modelocurriculum.net\/wp-content\/uploads\/2010\/03\/chronologicalcv4blue.jpg","thumb":"https:\/\/tse4.mm.bing.net\/th?id=OIP.mG7TbIqSHsrTjxzuMfbhkgHaKh&pid=Api&P=0&w=300&h=300"},{"judul":"warehouse logistics specialist resume sample","link":"https:\/\/imgv2-2-f.scribdassets.com\/img\/document\/12271255\/original\/b9ec1c9255\/1501053697","thumb":"https:\/\/tse1.mm.bing.net\/th?id=OIP.vV8NETDuSobDCjQJlUfrEgHaJ4&pid=Api&P=0&w=300&h=300"},{"judul":"web designer resume template   cover letter   portfolio","link":"http:\/\/www.cvfolio.com\/wp-content\/uploads\/Microsoft-Word-Web-Designer-Cover-Letter-Red.jpg","thumb":"https:\/\/tse4.mm.bing.net\/th?id=OIP.RtV7e7vdaI6IASGTNaOHbAHaK9&pid=Api&P=0&w=300&h=300"},{"judul":"12 software developer resume sample s","link":"https:\/\/www.resumeviking.com\/wp-content\/uploads\/2017\/11\/Elliot-Alderson-Resume-Software-Developer-9.jpg","thumb":"https:\/\/tse2.mm.bing.net\/th?id=OIP.L-JeE7-mvbzrnCPKwL2PIAHaKf&pid=Api&P=0&w=300&h=300"}]