[{"judul":"cv jacques duranteau","link":"https:\/\/image.slidesharecdn.com\/d925ca8f-69c5-4986-91b0-790633103cb7-160323173103\/95\/cv-jacques-duranteau-7-638.jpg?cb=1458754325","thumb":"https:\/\/tse3.mm.bing.net\/th?id=OIP.yBo3LLhhWwULThkMO2jD5wHaKe&pid=Api&P=0&w=300&h=300"},{"judul":"happy birthday to nidia","link":"https:\/\/pm1.narvii.com\/6766\/0d9c9908c45b9a13f95b34bdebec5bcbd52f751cv2_hq.jpg","thumb":"https:\/\/tse3.mm.bing.net\/th?id=OIP.XDMdmh2PLZRd9x9GvwF4WQHaIV&pid=Api&P=0&w=300&h=300"},{"judul":"candorville candorville  u00bb daily comics by darrin bell","link":"https:\/\/i1.wp.com\/candorville.com\/wp-content\/uploads\/2015\/04\/CV7-front-web.jpg","thumb":"https:\/\/tse3.mm.bing.net\/th?id=OIP.1QYs4NVYq4yOCJXturZd1gHaJq&pid=Api&P=0&w=300&h=300"},{"judul":"liberty  lies  and statistics","link":"https:\/\/www.catholicvote.org\/wp-content\/uploads\/2015\/05\/thomas_dolby-640x336.jpg","thumb":"https:\/\/tse1.mm.bing.net\/th?id=OIP.VZ0nv0Ym5JUnOB8fB5RlzQHaD4&pid=Api&P=0&w=300&h=300"},{"judul":"jonno davies  u00bb cv  resume","link":"http:\/\/www.jonnodavies.com\/wp-content\/uploads\/2017\/04\/6114.jpg","thumb":"https:\/\/tse1.mm.bing.net\/th?id=OIP.WIc6VHIXVjYv4LCgXUg_9gHaJQ&pid=Api&P=0&w=300&h=300"},{"judul":"lydia currie","link":"https:\/\/cdn.casarotto.co.uk\/images\/productions\/_listing13\/6.-REV.-www.youtube.com_watch_vzVWkCWWudvg.jpg?mtime=20180626185813","thumb":"https:\/\/tse4.mm.bing.net\/th?id=OIP.pqVkYTj7Ruoy880Wwg9oRwHaEP&pid=Api&P=0&w=300&h=300"},{"judul":"aha  emphasis","link":"https:\/\/image.slidesharecdn.com\/emphasis-hf-101115080855-phpapp02\/95\/aha-emphasishf-trial-10-728.jpg?cb=1358859127","thumb":"https:\/\/tse1.mm.bing.net\/th?id=OIP.M5cJFVECHaqhXi44rSgtjwHaFP&pid=Api&P=0&w=300&h=300"},{"judul":"jonno davies  u00bb jonno filming  u201cperceptions u201d","link":"http:\/\/www.jonnodavies.com\/wp-content\/uploads\/2014\/07\/Perceptions-1.jpg","thumb":"https:\/\/tse4.mm.bing.net\/th?id=OIP.2fjlVE0t2f6Via183LB8YQHaDw&pid=Api&P=0&w=300&h=300"},{"judul":"prints","link":"http:\/\/joakimallgulander.co.uk\/joakim\/wp-content\/uploads\/2014\/07\/Mushroom-Gasgrafik.jpg","thumb":"https:\/\/tse2.mm.bing.net\/th?id=OIP.ZmfXphZUm7QdJtAkX3IVPAHaJT&pid=Api&P=0&w=300&h=300"},{"judul":"u0026quot das quartett u0026quot   neuer zdf","link":"https:\/\/www.goldenekamera.de\/img\/incoming\/crop215806873\/4572606006-w820-cv16_9-q85\/quartett.jpg","thumb":"https:\/\/tse1.mm.bing.net\/th?id=OIP.ZN4n2ujk3wepeIpE-BXFOQHaEK&pid=Api&P=0&w=300&h=300"},{"judul":"oto","link":"http:\/\/3.bp.blogspot.com\/-uQBLForN8wM\/UoZJnCpD-sI\/AAAAAAAAEEU\/mcazdki7YBg\/s1600\/%E3%82%B9%E3%82%AF%E3%83%AA%E3%83%BC%E3%83%B3%E3%82%B7%E3%83%A7%E3%83%83%E3%83%88+2013-11-16+1.19.08.png","thumb":"https:\/\/tse4.mm.bing.net\/th?id=OIP.8vweVTJfXQtzzbjXZLGZDgHaDM&pid=Api&P=0&w=300&h=300"},{"judul":"plein air painting on speed  morning break","link":"https:\/\/i1.wp.com\/rebeccakinghawkinson.com\/wp-content\/uploads\/2016\/11\/Morning-Break.jpg","thumb":"https:\/\/tse3.mm.bing.net\/th?id=OIP.KhznAEUqUao_4x-YBsdRKwHaFg&pid=Api&P=0&w=300&h=300"},{"judul":"prints","link":"http:\/\/joakimallgulander.co.uk\/joakim\/wp-content\/uploads\/2014\/07\/lamp-deer.jpg","thumb":"https:\/\/tse4.mm.bing.net\/th?id=OIP.ugVYOwF9PN2dirjbm-FwfAHaJ1&pid=Api&P=0&w=300&h=300"},{"judul":"zoetis","link":"https:\/\/vetsmart-parsefiles.s3.amazonaws.com\/b5cf9c5cbfb32c360b20132532aa1b1b_imageInputImg.png","thumb":"https:\/\/tse3.mm.bing.net\/th?id=OIP.fynrdNIjHQ6xJhPg9xXCZgHaHt&pid=Api&P=0&w=300&h=300"}]