[{"judul":"concept moderne cv noir et blanc","link":"https:\/\/image.freepik.com\/vecteurs-libre\/concept-moderne-cv-noir-blanc_23-2147733105.jpg","thumb":"https:\/\/tse1.mm.bing.net\/th?id=OIP.lNv9Gnmoj7xFMIkf-ILYFQHaHa&pid=Api&P=0&w=300&h=300"},{"judul":"mod u00e8le cv cv","link":"https:\/\/image.freepik.com\/vecteurs-libre\/modele-cv-cv_1410-173.jpg","thumb":"https:\/\/tse4.mm.bing.net\/th?id=OIP.uh0yICHIgmUq4LFrLVPlkwHaHk&pid=Api&P=0&w=300&h=300"},{"judul":"concept de cv  u00e9l u00e9gant","link":"https:\/\/image.freepik.com\/vecteurs-libre\/concept-cv-elegant_23-2147735075.jpg","thumb":"https:\/\/tse3.mm.bing.net\/th?id=OIP.ntA1j38CYdR1iInUMdvGzAHaHa&pid=Api&P=0&w=300&h=300"},{"judul":"cv minimaliste    mod u00e8le de cv","link":"https:\/\/image.freepik.com\/vecteurs-libre\/cv-minimaliste-modele-cv_1151-414.jpg","thumb":"https:\/\/tse1.mm.bing.net\/th?id=OIP.PK9gpKAh7-Zzt9h9OC5l_wHaHa&pid=Api&P=0&w=300&h=300"},{"judul":"mod u00e8le de cv moderne","link":"https:\/\/image.freepik.com\/vecteurs-libre\/modele-cv-moderne_23-2147539948.jpg","thumb":"https:\/\/tse1.mm.bing.net\/th?id=OIP.kIwigkoD_vYEkkQvlgzYdAHaHa&pid=Api&P=0&w=300&h=300"},{"judul":"purple cv template","link":"https:\/\/image.freepik.com\/vecteurs-libre\/purple-cv-template_23-2147757370.jpg","thumb":"https:\/\/tse3.mm.bing.net\/th?id=OIP.n0RQfK4IWKsZKzysuf3u3QHaHa&pid=Api&P=0&w=300&h=300"},{"judul":"dark cv template","link":"https:\/\/image.freepik.com\/vecteurs-libre\/dark-cv-template_23-2147731097.jpg","thumb":"https:\/\/tse2.mm.bing.net\/th?id=OIP.SfV1OSRpY2yb5zBrmG078AHaHa&pid=Api&P=0&w=300&h=300"},{"judul":"beau mod u00e8le de cv","link":"https:\/\/image.freepik.com\/vecteurs-libre\/beau-modele-cv_23-2147658935.jpg","thumb":"https:\/\/tse4.mm.bing.net\/th?id=OIP.KdB3lYbB2Aufn3J06SfSlQHaHa&pid=Api&P=0&w=300&h=300"},{"judul":"cv illustratior dans des couleurs marron et orange","link":"https:\/\/image.freepik.com\/vecteurs-libre\/cv-illustratior-dans-couleurs-marron-orange_23-2147541995.jpg","thumb":"https:\/\/tse3.mm.bing.net\/th?id=OIP.sMRRcjCaJFEVAznb_T1zBwHaHa&pid=Api&P=0&w=300&h=300"},{"judul":"curriculum vitae mod u00e8le","link":"https:\/\/image.freepik.com\/vecteurs-libre\/curriculum-vitae-modele_1152-108.jpg","thumb":"https:\/\/tse4.mm.bing.net\/th?id=OIP.SXx5wUDwxVkNLQRQeygtXgHaIo&pid=Api&P=0&w=300&h=300"},{"judul":"mod u00e8le de cv f u00e9minin et  u00e9l u00e9gant","link":"https:\/\/image.freepik.com\/vecteurs-libre\/modele-cv-feminin-elegant_3785-46.jpg","thumb":"https:\/\/tse3.mm.bing.net\/th?id=OIP.f5Xhes6QF7aJYVqcrUr5rQHaHa&pid=Api&P=0&w=300&h=300"},{"judul":"tarte color u00e9 tableau infographique","link":"https:\/\/image.freepik.com\/vecteurs-libre\/tarte-colore-tableau-infographique_23-2147525010.jpg","thumb":"https:\/\/tse3.mm.bing.net\/th?id=OIP.o0q92LhHITOOXln4MaO-yAHaHa&pid=Api&P=0&w=300&h=300"},{"judul":"rapha u00ebl zacharie de izarra ovni warloy baillon ufo","link":"https:\/\/farm5.staticflickr.com\/4052\/4537103745_cb3bac88b2_b.jpg","thumb":"https:\/\/tse2.mm.bing.net\/th?id=OIP.UHJLAUIFgOm9Z98VGRJpgQHaKc&pid=Api&P=0&w=300&h=300"},{"judul":"rapha u00ebl zacharie de izarra ovni warloy baillon ufo","link":"http:\/\/2.bp.blogspot.com\/-XJ3hFQOjzas\/TaBiEzGscqI\/AAAAAAAAABU\/7jaRRODOpvk\/s640\/Rapha%25C3%25ABl+Zacharie+de+IZARRA+-+Warloy-Baillon+-+Farra+FAWCETT.jpg","thumb":"https:\/\/tse1.mm.bing.net\/th?id=OIP.EifJ_FfNd1sv4BdTGJzHnwHaHP&pid=Api&P=0&w=300&h=300"}]