[{"judul":"mgh cardiovascular images","link":"http:\/\/www.massgeneral.org\/radiology\/news\/cv-newsletter\/march_2014\/figure1.gif","thumb":"https:\/\/tse1.mm.bing.net\/th?id=OIP.g5wUNQaW774qVce3gu5qMgHaHB&pid=Api&P=0&w=300&h=300"},{"judul":"net neutrality  obama and oatmeal","link":"https:\/\/object.cato.org\/sites\/cato.org\/files\/multimedia\/2014\/cv-11-12-14.png","thumb":"https:\/\/tse3.mm.bing.net\/th?id=OIP.sRYNO5P1RXNYohK1RPZkZQHaEK&pid=Api&P=0&w=300&h=300"},{"judul":"renault 4 cv  1958","link":"https:\/\/www.classicargarage.com\/assets\/images\/5\/renault-4cv-02-4c2449e5.jpg","thumb":"https:\/\/tse2.mm.bing.net\/th?id=OIP.UEzjeU_aIaeaB03QrQQTbAHaE8&pid=Api&P=0&w=300&h=300"},{"judul":"sarah walsh photos photos - australia v usa","link":"http:\/\/www3.pictures.gi.zimbio.com\/Sarah+Walsh+Australia+v+USA+O630CV7_FMql.jpg","thumb":"https:\/\/tse2.mm.bing.net\/th?id=OIP.kMJvGA3UtNwMVRo2OHq6qgAAAA&pid=Api&P=0&w=300&h=300"},{"judul":"holland roden photos photos","link":"http:\/\/www4.pictures.zimbio.com\/gi\/Teen+Wolf+Final+Farewell+New+York+Comic+Con+XMJCET54CV9x.jpg","thumb":"https:\/\/tse3.mm.bing.net\/th?id=OIP.KO184WIlh2TGM-MVyPDqpAHaLG&pid=Api&P=0&w=300&h=300"},{"judul":"zwischen t u00fcll und tr u00e4nen","link":"https:\/\/img.bildderfrau.de\/img\/mode-schoenheit\/crop213330301\/5986634571-w820-cv16_9-q85-dc1\/Maritta-Emser-Geschaeft.jpg","thumb":"https:\/\/tse3.mm.bing.net\/th?id=OIP.Tr_FxCmLd29t3odPenJqdgHaEK&pid=Api&P=0&w=300&h=300"},{"judul":"c v","link":"http:\/\/s1.e-monsite.com\/2009\/08\/04\/10\/47142453ccf03082009-00000-jpg.jpg","thumb":"https:\/\/tse1.mm.bing.net\/th?id=OIP.D9-wtbyZMu_kxhGL6g_VWQHaKQ&pid=Api&P=0&w=300&h=300"},{"judul":"unterwegs mit jessy wellmer  im zweifel erfolgreich","link":"https:\/\/img.morgenpost.de\/img\/politik\/crop212311041\/61626086-w820-cv16_9-q85\/DSC-7424-047.jpg","thumb":"https:\/\/tse4.mm.bing.net\/th?id=OIP.JGnir16xJKNoDlMsqK_6UAHaEK&pid=Api&P=0&w=300&h=300"},{"judul":"rolf eden   u201efrauen sind immer sehr zufrieden mit mir","link":"https:\/\/img.morgenpost.de\/img\/incoming\/crop210045717\/0622608123-w820-cv16_9-q85\/DSC-3592.jpg","thumb":"https:\/\/tse1.mm.bing.net\/th?id=OIP.lEg9jD1KkuA0YS__WmkFEgHaEK&pid=Api&P=0&w=300&h=300"},{"judul":"gro u00dfer zapfenstreich zum 60  der bundeswehr","link":"https:\/\/img.morgenpost.de\/img\/politik\/crop206564555\/218260605-w820-cv16_9-q85\/148ED6001031AEF8-053.jpg","thumb":"https:\/\/tse4.mm.bing.net\/th?id=OIP.kKVE7z-h2FL-7iHZ3xfiGgHaEK&pid=Api&P=0&w=300&h=300"},{"judul":"hintergrund  weiblich  m u00e4nnlich  divers","link":"https:\/\/www.augsburger-allgemeine.de\/img\/politik\/crop43197856\/1076425952-cv16_9-w1200\/Copy-20of-20imago-st-1108-11180004-78132222.jpg","thumb":"https:\/\/tse1.mm.bing.net\/th?id=OIP.FGI-Q39UGqyv0AueQmvX9AHaEK&pid=Api&P=0&w=300&h=300"},{"judul":"rund 200 hosenlose fahren in berlin u-bahn","link":"https:\/\/img.morgenpost.de\/img\/incoming\/crop206905647\/2052607681-w820-cv16_9-q85\/Heute-fand-der-No-Pants-Subway-Ride-auch-in-Berlin-statt.jpg","thumb":"https:\/\/tse3.mm.bing.net\/th?id=OIP.WmmffSLvPOPpPay3WDs-iQHaEK&pid=Api&P=0&w=300&h=300"},{"judul":"test drive  alfa romeo giulietta tct 1 4 tb multiair 170","link":"https:\/\/www.italiantestdriver.com\/wp-content\/gallery\/test-drive-alfa-romeo-giulietta-tct\/test-drive-alfa-romeo-giulietta-tct-1-4-tbi-170-cv-11.jpg","thumb":"https:\/\/tse2.mm.bing.net\/th?id=OIP.RaOk8ELlqT_OlMxXBI_z-gHaFj&pid=Api&P=0&w=300&h=300"},{"judul":"cat u00e1logo vicky form","link":"http:\/\/i-vickyform.a8e.net.br\/static\/images\/sb-trends-18-1.jpg","thumb":"https:\/\/tse4.mm.bing.net\/th?id=OIP.BPZT5cNWQcmi3gEYMgeeVQHaJ0&pid=Api&P=0&w=300&h=300"}]