[{"judul":"resume sample film smlf format your film theatre or acting","link":"https:\/\/i.pinimg.com\/originals\/e2\/d4\/0f\/e2d40f365469a47cb3b90dd0367604af.jpg","thumb":"https:\/\/tse2.mm.bing.net\/th?id=OIP.RJvxjzLzNxA1A_YQC_JyBQHaJl&pid=Api&P=0&w=300&h=300"},{"judul":"production runner cv example  kode media the guardian","link":"https:\/\/resumesearchstorage.blob.core.windows.net\/ukimages\/164\/100\/471\/111755775_164100471.jpg","thumb":"https:\/\/tse2.mm.bing.net\/th?id=OIP.yA_pZ7pz0aBoQMS0RFGh1AHaIq&pid=Api&P=0&w=300&h=300"},{"judul":"11 amazing media  u0026 entertainment resume examples","link":"https:\/\/www.livecareer.com\/images\/uploaded\/resume-examples-expanded\/film-crew-media-entertainment-modern-1.jpg","thumb":"https:\/\/tse1.mm.bing.net\/th?id=OIP.d4f3-irQsdoQtKWQtLAkBwHaJl&pid=Api&P=0&w=300&h=300"},{"judul":"acting resume no experience template    topresume","link":"https:\/\/s-media-cache-ak0.pinimg.com\/736x\/12\/4f\/b1\/124fb1881a785aacec47e313e1c9996d--acting-resume-template-sample-resume.jpg","thumb":"https:\/\/tse1.mm.bing.net\/th?id=OIP.LqRCi7I75lMgSlTSAPEd2QHaJQ&pid=Api&P=0&w=300&h=300"},{"judul":"photographer resume  sample and full writing guide  20","link":"https:\/\/cdn-images.zety.com\/pages\/sample_photographer_resume.jpg","thumb":"https:\/\/tse1.mm.bing.net\/th?id=OIP.JKE59SLQsDYuXnfg5TctXAHaD8&pid=Api&P=0&w=300&h=300"},{"judul":"internship resume sample","link":"https:\/\/media.newjobs.com\/seo-media\/us\/resume-images\/film-industry-internship.jpg","thumb":"https:\/\/tse3.mm.bing.net\/th?id=OIP.TykoOiJlui9S4s-ihj_nKgHaJl&pid=Api&P=0&w=300&h=300"},{"judul":"7 sample photographer resume templates to download","link":"https:\/\/images.sampletemplates.com\/wp-content\/uploads\/2015\/08\/sample-photographer-resume.jpg","thumb":"https:\/\/tse2.mm.bing.net\/th?id=OIP.4dW8Zdy2AsG6-RYVWBIW7gHaIu&pid=Api&P=0&w=300&h=300"},{"judul":"social media cover letter example","link":"https:\/\/resumegenius.com\/wp-content\/uploads\/2018\/12\/Social-Media-Cover-Letter-Example-Template.png","thumb":"https:\/\/tse4.mm.bing.net\/th?id=OIP.JBF8kDYpgl_XvMu_1LmJbgHaKe&pid=Api&P=0&w=300&h=300"},{"judul":"psd resume template  u2013 51  free samples  examples  format","link":"https:\/\/images.template.net\/wp-content\/uploads\/2016\/01\/12110339\/Creative-Director-Resume-Template.jpg","thumb":"https:\/\/tse2.mm.bing.net\/th?id=OIP.-OJBAn3W4zu2mf0uLjDMcQHaF7&pid=Api&P=0&w=300&h=300"},{"judul":"t300 garage built - rocketgarage","link":"https:\/\/4.bp.blogspot.com\/-4WHw3NdIeeM\/VyJSj5odXDI\/AAAAAAACVZk\/ALNwCImrD-8zJmDjirgLZ9Cv-XN8u846wCLcB\/s1600\/T300%2BGarage%2BBuilt-003.jpg","thumb":"https:\/\/tse2.mm.bing.net\/th?id=OIP.Wgoc8CncEHEWYYEEUrj0xQHaEn&pid=Api&P=0&w=300&h=300"},{"judul":"mall of lahore website design","link":"https:\/\/mazcreative.files.wordpress.com\/2012\/12\/bahria_mall_of_lahore.jpg","thumb":"https:\/\/tse3.mm.bing.net\/th?id=OIP.sSbzzJGQWxv2kw8oc4YecQEsDs&pid=Api&P=0&w=300&h=300"},{"judul":"an exclusive preview of wonder woman  0","link":"http:\/\/images.huffingtonpost.com\/2012-09-18-WW_Cv0_ds-thumb.jpg","thumb":"https:\/\/tse4.mm.bing.net\/th?id=OIP.gkQWv94djsdGAGZpY1ATnAHaLY&pid=Api&P=0&w=300&h=300"},{"judul":"radio resume samples","link":"https:\/\/www.velvetjobs.com\/resume\/radio-resume-sample.jpg","thumb":"https:\/\/tse3.mm.bing.net\/th?id=OIP.5y7vroWcETnKe7Xs8NsOLgHaKr&pid=Api&P=0&w=300&h=300"},{"judul":"newspaper  u0026 magazine ads","link":"https:\/\/mazcreative.files.wordpress.com\/2013\/01\/curemd-newspaper-ad-nov-2005.jpg","thumb":"https:\/\/tse2.mm.bing.net\/th?id=OIP.a5TUEeknvqa0AfNWW7wofAHaLA&pid=Api&P=0&w=300&h=300"}]