[{"judul":"exemple de cv word original","link":"https:\/\/www.cv-word.com\/125-225-thickbox\/exemple-modele-cv-educateur-specialise.jpg","thumb":"https:\/\/tse2.mm.bing.net\/th?id=OIP.f1C9COb0KaqwhJC3xp6pOQHaHa&pid=Api&P=0&w=300&h=300"},{"judul":"t u00e9l u00e9charger mod u00e8le cv word original gestionnaire de client u00e8le","link":"https:\/\/www.cv-word.com\/111-191-thickbox\/exemple-modele-cv-word-gestionnaire-de-clientele.jpg","thumb":"https:\/\/tse1.mm.bing.net\/th?id=OIP.thVotHWCiAtwb1wnFV29jwHaHa&pid=Api&P=0&w=300&h=300"},{"judul":"exemple mod u00e8le cv word conducteur de travaux","link":"https:\/\/www.cv-word.com\/115-195-thickbox\/exemple-modele-cv-word-conducteur-de-travaux.jpg","thumb":"https:\/\/tse1.mm.bing.net\/th?id=OIP.K5TquFe49QUNAZmfyFgVaAHaHa&pid=Api&P=0&w=300&h=300"},{"judul":"cv mod u00e8le moderne 1 - word  u00e0 t u00e9l u00e9charger","link":"https:\/\/cvexemple.com\/wp-content\/uploads\/cv-model-new-2-copy.png","thumb":"https:\/\/tse3.mm.bing.net\/th?id=OIP.a_jwPQPD0b2McN_RgbVYpwHaER&pid=Api&P=0&w=300&h=300"},{"judul":"mod u00e8le lettre de motivation esth u00e9ticienne  u00e0 t u00e9l u00e9charger en","link":"https:\/\/www.cv-word.com\/48-130-thickbox\/lettre-de-motivation-estheticienne.jpg","thumb":"https:\/\/tse1.mm.bing.net\/th?id=OIP.0NqPpyeS3FTOhIJpMFiI9gHaHa&pid=Api&P=0&w=300&h=300"},{"judul":"cv laurapaulmard2013 par laura","link":"https:\/\/www.fichier-pdf.fr\/2013\/10\/08\/cv-laurapaulmard2013\/preview-cv-laurapaulmard2013-1.jpg","thumb":"https:\/\/tse2.mm.bing.net\/th?id=OIP.PDEtbz3JgF672vvgriQA1AHaJ4&pid=Api&P=0&w=300&h=300"},{"judul":"cv architecte","link":"https:\/\/cvexemple.com\/wp-content\/uploads\/Slide4.jpg","thumb":"https:\/\/tse1.mm.bing.net\/th?id=OIP.Yur7O3X1jfmr6H8Y0tJUVwHaKd&pid=Api&P=0&w=300&h=300"},{"judul":"mise en page cv word","link":"http:\/\/www.boite-lettres.com\/images\/mise-en-page-cv-word_1.jpg","thumb":"https:\/\/tse2.mm.bing.net\/th?id=OIP.uh23xlpNkeW5bMYsWfouwwHaKe&pid=Api&P=0&w=300&h=300"},{"judul":"dalston","link":"https:\/\/images.rezumeet.com\/2015\/12\/Dalston-Modele-CV-Gratuit.png","thumb":"https:\/\/tse4.mm.bing.net\/th?id=OIP.bM5OeIuvGA_pDWqAdc8s3QHaJ4&pid=Api&P=0&w=300&h=300"},{"judul":"oussama","link":"https:\/\/image.slidesharecdn.com\/oussama-100419062652-phpapp01\/95\/oussama-1-728.jpg?cb=1271658479","thumb":"https:\/\/tse4.mm.bing.net\/th?id=OIP.LETUZrv1oGrVeFjDT7gXCAHaKe&pid=Api&P=0&w=300&h=300"},{"judul":"le cv cr u00e9atif pour mettre en avant sa personnalit u00e9 chez","link":"https:\/\/multicomm.fr\/wp-content\/uploads\/2016\/12\/cv-Alice-comm-01-01-01-560x800.png","thumb":"https:\/\/tse2.mm.bing.net\/th?id=OIP.Oin-jKukNeNtWqNoitXJ7AHaKl&pid=Api&P=0&w=300&h=300"},{"judul":"candidature","link":"https:\/\/fanelacreative.files.wordpress.com\/2012\/09\/cv-marion.jpg","thumb":"https:\/\/tse2.mm.bing.net\/th?id=OIP.exOAHdC_cpLJ-4y4EBEQPQHaKe&pid=Api&P=0&w=300&h=300"},{"judul":"30 exemples superbes de cartes de visite","link":"http:\/\/www.presse-citron.net\/wordpress_prod\/wp-content\/uploads\/cv02.jpg","thumb":"https:\/\/tse4.mm.bing.net\/th?id=OIP.wJ2jwG7A_OqVmJRHMVNPEQHaFl&pid=Api&P=0&w=300&h=300"},{"judul":"cv de jeremy duluard au format a4 - cv 2014 pdf","link":"http:\/\/www.fichier-pdf.fr\/2014\/10\/01\/cv-2014\/preview-cv-2014-1.jpg","thumb":"https:\/\/tse1.mm.bing.net\/th?id=OIP.GdvEPRqKw9N-vnwKCAqk3gHaJ4&pid=Api&P=0&w=300&h=300"}]