[{"judul":"november 2015 marathi kalnirnay calendar","link":"https:\/\/i.pinimg.com\/originals\/65\/42\/71\/654271204e0622559fa9ba6f2dc5b9f9.jpg","thumb":"https:\/\/tse3.mm.bing.net\/th?id=OIP.ZUJxIE4GIlWfqbpvLcW5-QHaJO&pid=Api&P=0&w=300&h=300"},{"judul":"november 2015 marathi kalnirnay calendar","link":"https:\/\/s-media-cache-ak0.pinimg.com\/736x\/65\/42\/71\/654271204e0622559fa9ba6f2dc5b9f9.jpg","thumb":"https:\/\/tse2.mm.bing.net\/th?id=OIP.99oqVrfwzixGiDWdMmckSgHaJO&pid=Api&P=0&w=300&h=300"},{"judul":"marathi calendar 2019 pdf version  download  free","link":"http:\/\/www.marathi-unlimited.in\/wp-content\/uploads\/2018\/10\/January-2019-Marathi-Calendar-free-download.jpg","thumb":"https:\/\/tse4.mm.bing.net\/th?id=OIP.DhT7tpC0CvdUyk5pps8EMgHaFu&pid=Api&P=0&w=300&h=300"},{"judul":"october kalnirnay calendar 2018","link":"https:\/\/www.onlinecalendars.in\/wp-content\/uploads\/2017\/10\/October-kalnirnay-calendar-2018.jpg","thumb":"https:\/\/tse2.mm.bing.net\/th?id=OIP.NtKgGfd1_W6rq-LauSnC9wHaFR&pid=Api&P=0&w=300&h=300"},{"judul":"july month kalnirnay calendar 2018","link":"https:\/\/www.onlinecalendars.in\/wp-content\/uploads\/2017\/10\/July-month-kalnirnay-calendar-2018.jpg","thumb":"https:\/\/tse1.mm.bing.net\/th?id=OIP.TZlP6dGwT94b-iiKkyrTRQHaFQ&pid=Api&P=0&w=300&h=300"},{"judul":"u092e u0930 u093e u0920 u0940  u0915 u093e u0932 u0928 u093f u0930 u094d u0923 u092f  u0915 u0945 u0932 u0947 u0902 u0921 u0930  u0968 u0966 u0967 u096f","link":"https:\/\/i.pinimg.com\/736x\/ab\/60\/57\/ab60577d2f20bc2ddf29f46b56a29220.jpg","thumb":"https:\/\/tse3.mm.bing.net\/th?id=OIP.unNA7QhsaCpLMF8GINKIGQAAAA&pid=Api&P=0&w=300&h=300"},{"judul":"2019 kalnirnay marathi calendars 2018","link":"https:\/\/www.onlinecalendars.in\/wp-content\/uploads\/2016\/11\/October-kalnirnay-calendar-2017.jpg","thumb":"https:\/\/tse4.mm.bing.net\/th?id=OIP.ZvsEFNxO3hRFahWUAaYuggHaEJ&pid=Api&P=0&w=300&h=300"},{"judul":"marathi calendar 2018 free pdf download  gharoghari","link":"https:\/\/www.marathi-unlimited.in\/wp-content\/uploads\/2017\/10\/March-2018-Marathi-Calendar-PDF-Free-Download.jpg","thumb":"https:\/\/tse3.mm.bing.net\/th?id=OIP.PDh9TDqA64xTjeRpP8TJogHaFu&pid=Api&P=0&w=300&h=300"},{"judul":"u092e u0930 u093e u0920 u0940  u0915 u093e u0932 u0928 u093f u0930 u094d u0923 u092f  u0915 u0945 u0932 u0947 u0902 u0921 u0930  u0968 u0966 u0967 u096c","link":"https:\/\/4.bp.blogspot.com\/-NU0BqJvk61U\/VozbLpB_R5I\/AAAAAAAAD8s\/FLUrUw-9K2Q\/s1600\/12-marathi-kalnirnay-calendar-december-2016.jpg","thumb":"https:\/\/tse3.mm.bing.net\/th?id=OIP.FJaFaM9XyBTxvAEKovgejgHaLS&pid=Api&P=0&w=300&h=300"},{"judul":"october 2018 kalnirnay calendar marathi  hindi  gujarati","link":"https:\/\/ecuafiestastematicas.com\/wp-content\/uploads\/2018\/09\/Kalnirnay-2018-October-Calendar.jpg","thumb":"https:\/\/tse2.mm.bing.net\/th?id=OIP.Xd6dmIR3A_3aaNm5RD75BgHaHa&pid=Api&P=0&w=300&h=300"},{"judul":"december month mahalaxmi marathi calendar 2017","link":"http:\/\/www.onlinecalendars.in\/wp-content\/uploads\/2016\/12\/December-month-mahalaxmi-calendar-2017.jpg","thumb":"https:\/\/tse3.mm.bing.net\/th?id=OIP.nTCqpv1pgYrYz-KahqIfTQHaIj&pid=Api&P=0&w=300&h=300"},{"judul":"kalnirnay 2015 marathi pdf","link":"http:\/\/ephesustour.cc\/wp-content\/uploads\/random-kalnirnay-2015-marathi-pdf.jpg","thumb":"https:\/\/tse4.mm.bing.net\/th?id=OIP.ahLuI8A4kekW6ZeRVoK2uAHaJO&pid=Api&P=0&w=300&h=300"},{"judul":"2019 kalnirnay marathi calendars 2018","link":"http:\/\/www.onlinecalendars.in\/wp-content\/uploads\/2016\/12\/November-Month-Narendra-Maharaj-Calendar-2017.png","thumb":"https:\/\/tse2.mm.bing.net\/th?id=OIP.bXfzkto04IAte2BinDjw4AHaI3&pid=Api&P=0&w=300&h=300"},{"judul":"2019 kalnirnay marathi calendars 2018","link":"https:\/\/www.onlinecalendars.in\/wp-content\/uploads\/2016\/12\/september-month-mahalaxmi-calendar-2017.jpg","thumb":"https:\/\/tse2.mm.bing.net\/th?id=OIP.kF2J9JWUt76gU4GkbVKKCgHaJK&pid=Api&P=0&w=300&h=300"}]