[{"judul":"formation graphisme et communication visuelle","link":"http:\/\/blog.crdp-versailles.fr\/fcil2009ejm\/public\/Seznec\/Candodatures\/Candidatures-session.jpg","thumb":"https:\/\/tse3.mm.bing.net\/th?id=OIP.KGZzS654ZQbe_ZGuYuckvQHaEf&pid=Api&P=0&w=300&h=300"},{"judul":"sortie  u00e0 chaumont - lyc u00e9e corvisart-tolbiac","link":"https:\/\/lycee-corvisart-tolbiac.fr\/images\/m-daveiga\/2017-18\/SORTIE\/chaumont\/IMG_1006.jpg","thumb":"https:\/\/tse2.mm.bing.net\/th?id=OIP.WuJG4SQoaKcsoWkQtuX6VgHaFj&pid=Api&P=0&w=300&h=300"}]